<?xml version="1.0" encoding="utf-8" ?>
<dwsync>
<file name="IMG_0415.JPG" server="27.254.172.28/public_html/" local="128768421402656250" remote="132810793200000000" Dst="0" />
<file name="IMG_0416.JPG" server="27.254.172.28/public_html/" local="128768422198593750" remote="132810793200000000" Dst="0" />
<file name="P1040041.JPG" server="27.254.172.28/public_html/" local="128768421408593750" remote="132810793200000000" Dst="0" />
<file name="P1040043.JPG" server="27.254.172.28/public_html/" local="128768421410312500" remote="132810793200000000" Dst="0" />
<file name="P1040046.JPG" server="27.254.172.28/public_html/" local="128768421412031250" remote="132810793200000000" Dst="0" />
<file name="P1040047.JPG" server="27.254.172.28/public_html/" local="128768422200312500" remote="132810793200000000" Dst="0" />
<file name="991176.php" server="27.254.172.28/public_html/" local="132888641400000000" remote="132888641400000000" Dst="0" />
<file name="ffAA531.php" server="27.254.172.28/public_html/" local="132888642000000000" remote="132888642000000000" Dst="0" />
</dwsync>