<?xml version="1.0" encoding="utf-8" ?>
<dwsync>
<file name="IMG_0061_resize.JPG" server="27.254.172.28/public_html/" local="132810822600000000" remote="132810822600000000" Dst="0" />
<file name="IMG_0062_resize.JPG" server="27.254.172.28/public_html/" local="132810822600000000" remote="132810822600000000" Dst="0" />
<file name="IMG_0063_resize.JPG" server="27.254.172.28/public_html/" local="132810822600000000" remote="132810822600000000" Dst="0" />
<file name="IMG_0064_resize.JPG" server="27.254.172.28/public_html/" local="132810822600000000" remote="132810822600000000" Dst="0" />
<file name="IMG_0065_resize.JPG" server="27.254.172.28/public_html/" local="132810822600000000" remote="132810822600000000" Dst="0" />
<file name="IMG_0066_resize.JPG" server="27.254.172.28/public_html/" local="132810822600000000" remote="132810822600000000" Dst="0" />
<file name="IMG_0068_resize.JPG" server="27.254.172.28/public_html/" local="132810874200000000" remote="132810874200000000" Dst="0" />
<file name="IMG_0069_resize.JPG" server="27.254.172.28/public_html/" local="132810822600000000" remote="132810822600000000" Dst="0" />
<file name="IMG_0070_resize.JPG" server="27.254.172.28/public_html/" local="132810822600000000" remote="132810822600000000" Dst="0" />
<file name="IMG_0071_resize.JPG" server="27.254.172.28/public_html/" local="132810822600000000" remote="132810822600000000" Dst="0" />
<file name="IMG_0073_resize.JPG" server="27.254.172.28/public_html/" local="132810822600000000" remote="132810822600000000" Dst="0" />
<file name="IMG_0074_resize.JPG" server="27.254.172.28/public_html/" local="132810822600000000" remote="132810822600000000" Dst="0" />
<file name="IMG_0075_resize.JPG" server="27.254.172.28/public_html/" local="132810822600000000" remote="132810822600000000" Dst="0" />
<file name="IMG_0076_resize.JPG" server="27.254.172.28/public_html/" local="132810822600000000" remote="132810822600000000" Dst="0" />
<file name="IMG_0077_resize.JPG" server="27.254.172.28/public_html/" local="132810822600000000" remote="132810822600000000" Dst="0" />
<file name="IMG_0078_resize.JPG" server="27.254.172.28/public_html/" local="132810822600000000" remote="132810822600000000" Dst="0" />
<file name="IMG_0079_resize.JPG" server="27.254.172.28/public_html/" local="132810822600000000" remote="132810822600000000" Dst="0" />
<file name="IMG_0080_resize.JPG" server="27.254.172.28/public_html/" local="132810874200000000" remote="132810874200000000" Dst="0" />
<file name="IMG_0081_resize.JPG" server="27.254.172.28/public_html/" local="132810874200000000" remote="132810874200000000" Dst="0" />
<file name="IMG_0082_resize.JPG" server="27.254.172.28/public_html/" local="132810823200000000" remote="132810823200000000" Dst="0" />
</dwsync>