<?xml version="1.0" encoding="utf-8" ?>
<dwsync>
<file name="P8010023_resize.JPG" server="27.254.172.28/public_html/" local="132810820200000000" remote="132810820200000000" Dst="0" />
<file name="P8010024_resize.JPG" server="27.254.172.28/public_html/" local="132810820200000000" remote="132810820200000000" Dst="0" />
<file name="P8010025_resize.JPG" server="27.254.172.28/public_html/" local="132810874200000000" remote="132810874200000000" Dst="0" />
<file name="P8010026_resize.JPG" server="27.254.172.28/public_html/" local="132810820200000000" remote="132810820200000000" Dst="0" />
<file name="P8010027_resize.JPG" server="27.254.172.28/public_html/" local="132810820200000000" remote="132810820200000000" Dst="0" />
<file name="P8010028_resize.JPG" server="27.254.172.28/public_html/" local="132810820200000000" remote="132810820200000000" Dst="0" />
<file name="P8010032_resize.JPG" server="27.254.172.28/public_html/" local="132810820200000000" remote="132810820200000000" Dst="0" />
<file name="P8010033_resize.JPG" server="27.254.172.28/public_html/" local="132810820200000000" remote="132810820200000000" Dst="0" />
<file name="P8010034_resize.JPG" server="27.254.172.28/public_html/" local="132810820200000000" remote="132810820200000000" Dst="0" />
<file name="P8010035_resize.JPG" server="27.254.172.28/public_html/" local="132810820200000000" remote="132810820200000000" Dst="0" />
<file name="P8010036_resize.JPG" server="27.254.172.28/public_html/" local="132810820200000000" remote="132810820200000000" Dst="0" />
<file name="P8010037_resize.JPG" server="27.254.172.28/public_html/" local="132810820200000000" remote="132810820200000000" Dst="0" />
<file name="P8010038_resize.JPG" server="27.254.172.28/public_html/" local="132810820200000000" remote="132810820200000000" Dst="0" />
</dwsync>